triplettorch/__init__.py
triplettorch/data.py
triplettorch/loss.py
TripletTorch-0.1.3.dist-info/METADATA
TripletTorch-0.1.3.dist-info/WHEEL
TripletTorch-0.1.3.dist-info/top_level.txt
TripletTorch-0.1.3.dist-info/RECORD
