Metadata-Version: 2.1
Name: TripletTorch
Version: 0.1.3
Summary: Triplet Loss Utils for Pytorch Library.
Home-page: https://github.com/TowardHumanizedInteraction/TripletTorch
Author: yliess
Author-email: hatiyliess86@gmail.com
License: MIT
Platform: UNKNOWN
Requires-Python: >=3.4, <4
Requires-Dist: numpy (==1.17.2)
Requires-Dist: torch (==1.2.0)
Requires-Dist: torchvision (==0.4.0)
Requires-Dist: tqdm (==4.36.1)
Requires-Dist: matplotlib (==3.1.1)
